{
  "hero": {
    "eyebrow": "ברוכים הבאים",
    "titleLine1": "שלום, אני נועה,",
    "titleAccent": "מרחב לטיפול וצמיחה",
    "lead": "עו\"ס קלינית (MSW), מדריכה ופסיכותרפיסטית . מלווה מבוגרים בתהליך של היכרות עם עצמם, צמיחה ושינוי — בקליניקה בתל אביב ואונליין מכל מקום.",
    "sub": "אני מאמינה בכוחו של קשר טיפולי סבלני ומותאם אישית לאפשר תנועה וחופש — גם במצבים של קושי, תקיעות ומשבר.",
    "ctaPrimary": "לתיאום שיחת היכרות",
    "ctaSecondary": "עוד עליי",
    "photo": "/assets/images/noa.jpg",
    "photoAlt": "נועה ארנטל — פסיכותרפיסטית",
    "badgeTitle": "תל אביב",
    "badgeSub": "קליניקה · ואונליין"
  },
  "trustStrip": [
    "עו\"ס קלינית · MSW",
    "פסיכותרפיסטית ומדריכה",
    "מומחית לטיפול אונליין",
    "עברית · אנגלית"
  ],
  "online": {
    "eyebrow": "טיפול אונליין",
    "title": "תמיכה רגשית, נגישה מכל מקום",
    "p1": "טיפול אונליין הוא תחום ההתמחות שלי: אני משמשת כמנהלת המקצועית הארצית של שירות הפסיכותרפיה המקוונת בחברת שר\"ן, ומלווה ומדריכה צוותי מטפלים. אני מביאה את הניסיון הזה גם לטיפול הפרטי שלי.",
    "p2": "טיפול מקוון מאפשר ליווי מקצועי ורציף לכל מי שגרים רחוק, נמצאים בחו\"ל או עם לו\"ז צפוף — מבלי לוותר על איכות הקשר הטיפולי. לצד הקליניקה הפרטית בתל אביב, אני מטפלת אונליין מכל מקום, בסביבה בטוחה ודיסקרטית.",
    "cta": "לייעוץ לגבי טיפול אונליין",
    "checklist": [
      "גמיש ונגיש — מכל מקום בארץ ובעולם",
      "דיסקרטי ומותאם אישית",
      "רצף טיפולי ללא תלות במרחק",
      "גם בקליניקה בתל אביב וגם בזום"
    ]
  },
  "methods": {
    "eyebrow": "גישה ושיטות",
    "title": "גישה אינטגרטיבית, מותאמת אליך",
    "sub": "שילוב של טיפול דינמי \"קלאסי\" עם כלים מבוססי מחקר — מתוך קשיבות לחוויה הרגשית, הגופנית והבין־אישית.",
    "cards": [
      {
        "tag": "דינמי",
        "text": "טיפול פסיכודינמי"
      },
      {
        "tag": "CBT",
        "text": "קוגניטיבי־התנהגותי"
      },
      {
        "tag": "ACT",
        "text": "קבלה ומחויבות"
      },
      {
        "tag": "DBT",
        "text": "דיאלקטי התנהגותי"
      },
      {
        "tag": "סכמה",
        "text": "סכמה תרפיה"
      },
      {
        "tag": "מיינדפולנס",
        "text": "קשיבות ועבודה עם הגוף"
      }
    ]
  },
  "steps": {
    "eyebrow": "איך מתחילים",
    "title": "הדרך אל הפגישה הראשונה",
    "items": [
      {
        "title": "פנייה ראשונית",
        "text": "משאירים פרטים בטופס, בטלפון או בוואטסאפ — ואחזור אליכם בהקדם."
      },
      {
        "title": "שיחת היכרות",
        "text": "שיחה להבין מה מביא אתכם, ולחשוב יחד על הטיפול המתאים והמדויק ביותר עבורכם."
      },
      {
        "title": "תהליך מותאם",
        "text": "בונים יחד מרחב בטוח, לא שיפוטי ומחזיק — בקצב שלכם ובדרך שנכונה לכם."
      }
    ]
  },
  "practical": {
    "eyebrow": "פרטים מעשיים",
    "title": "מה חשוב לדעת",
    "items": [
      {
        "label": "איפה",
        "text": "בקליניקה בתל אביב, או אונליין בשיחת וידאו — מכל מקום בארץ ובעולם"
      },
      {
        "label": "למי",
        "text": "מבוגרים, ונוער מגיל 16"
      },
      {
        "label": "באיזו שפה",
        "text": "עברית ואנגלית"
      },
      {
        "label": "הכרה",
        "text": "ספקית מוכרת של משרד הביטחון — אגף משפחות"
      }
    ]
  },
  "quote": {
    "text": "אני מאמינה בכוחו של קשר טיפולי סבלני ומותאם אישית — לאפשר צמיחה, חופש ותנועה, גם במצבים של קושי, תקיעות ומשבר.",
    "cite": "— נועה ארנטל, עו\"ס קלינית ופסיכותרפיסטית"
  },
  "areas": {
    "eyebrow": "תחומי טיפול",
    "title": "התחומים בהם אני מלווה",
    "sub": "מלווה נוער (מעל גיל 16), נשים וגברים בהתמודדויות מגוונות:",
    "pills": [
      {
        "label": "חרדה",
        "url": "/anxiety/"
      },
      {
        "label": "דיכאון",
        "url": "/depression/"
      },
      {
        "label": "שכול ואובדן",
        "url": "/grief/"
      },
      {
        "label": "פוסט טראומה",
        "url": "/trauma/"
      },
      {
        "label": "העצמה נשית",
        "url": "/women/"
      },
      {
        "label": "טיפול מותאם לקהילה הגאה",
        "url": "/lgbtq/"
      },
      {
        "label": "משברי חיים",
        "url": ""
      },
      {
        "label": "התמכרויות ותחלואה כפולה",
        "url": ""
      },
      {
        "label": "זהות, מיניות ומגדר",
        "url": "/lgbtq/"
      },
      {
        "label": "קשיים בינאישיים ודימוי עצמי",
        "url": ""
      }
    ]
  },
  "faqSection": {
    "eyebrow": "שאלות נפוצות",
    "title": "שאלות שאולי עולות לך",
    "items": [
      {
        "q": "איך יודעים אם טיפול מתאים לי?",
        "a": "לא חייבים לדעת מראש. הצעד הראשון הוא שיחת היכרות קצרה וללא התחייבות — נכיר, נבין מה מביא אותך, ונחשוב יחד אם ואיך הטיפול יכול לעזור."
      },
      {
        "q": "האם טיפול אונליין באמת יעיל?",
        "a": "כן. מחקרים מראים שטיפול מקוון יעיל לא פחות מטיפול פנים אל פנים. זהו תחום ההתמחות שלי — אני מנהלת ומדריכה צוותי מטפלים בשירות פסיכותרפיה מקוונת, ומביאה את הניסיון הזה לכל פגישה."
      },
      {
        "q": "כמה זמן נמשך תהליך טיפולי?",
        "a": "זה משתנה מאדם לאדם ותלוי במטרות ובקצב שלך. יש תהליכים קצרים וממוקדים ויש מתמשכים יותר. נגדיר יחד מטרות ונבחן את ההתקדמות לאורך הדרך."
      },
      {
        "q": "מה נשאר חסוי?",
        "a": "הכול. על המידע שנמסר בטיפול חלה חובת סודיות מקצועית מלאה, בהתאם לכללי האתיקה של העובדים הסוציאליים ולחוק."
      },
      {
        "q": "איך מתחילים?",
        "a": "משאירים פרטים בטופס, בטלפון או בוואטסאפ, ואחזור אליכם לתיאום שיחת היכרות ראשונית. משם נמשיך יחד בקצב שמתאים לכם."
      }
    ]
  },
  "contact": {
    "eyebrow": "צור קשר",
    "title": "בואו נהיה בקשר",
    "text": "ההחלטה לפנות לטיפול היא צעד אמיץ. אני מזמינה אתכם להתייעץ איתי בלי התחייבות — מלאו פרטים ואחזור אליכם בהקדם."
  }
}
